mfn_cli/__init__.py
mfn_cli/cli.py
mfn_cli-0.8.9.dist-info/LICENSE
mfn_cli-0.8.9.dist-info/METADATA
mfn_cli-0.8.9.dist-info/WHEEL
mfn_cli-0.8.9.dist-info/entry_points.txt
mfn_cli-0.8.9.dist-info/top_level.txt
mfn_cli-0.8.9.dist-info/RECORD
