Metadata-Version: 2.1
Name: mfn-cli
Version: 0.8.9
Summary: KNIX MicroFunctions Command Line Interface
Home-page: https://github.com/knix-microfunctions/knix
Author: The KNIX authors
Author-email: knix-dev@list.nokia.com
License: Apache-2.0
Platform: UNKNOWN
Classifier: Programming Language :: Python :: 3
Classifier: Operating System :: OS Independent
Requires-Python: >=3.6
Requires-Dist: mfn-sdk (>="0.8.9")
Requires-Dist: click
